{
    "name": "Yoojung",
    "description": "Choi Yoojung/최유정, Yoodang",
    "picture": "https://cdn.discordapp.com/attachments/265561393430790144/265592101910216706/unknown.png",
    "birthday": "November 12, 1999",
    "birthplace": "South Korea",
    "bloodtype": "O",
    "height": "159 cm (~5'2)",
    "weight": "44 kg (~97lbs)",
    "position_in_group": "TBA",
    "languages": "Korean",
    "hobbies": "painting, photography",
    "colour": "2ECC71",
    "skills": "flexibility, dance, rap, vocal",
    "training": "2011-present",
    "education": "Seoul Music High School",
    "strengths": "Cheerful, Love to smile, Sociable",
    "weaknesses": "Slow to open up to strangers"
}
